flyf/__init__.py
flyf/chat.py
flyf-0.0.4.dist-info/licenses/LICENSE
flyf-0.0.4.dist-info/METADATA
flyf-0.0.4.dist-info/WHEEL
flyf-0.0.4.dist-info/entry_points.txt
flyf-0.0.4.dist-info/top_level.txt
flyf-0.0.4.dist-info/RECORD
