Metadata-Version: 2.4
Name: flyf
Version: 0.0.4
Summary: 一个致力于打造最好用最方便的AI使用工具
Home-page: https://github.com/AiFLYF/flyf
Author: FLYF
Author-email: flyf@94209420.xyz
License: Apache-2.0
Keywords: chat,Windows,Linux,MacOS,chatgpt,openai,aitool,ai工具,ai聊天工具,flyf,FLYFAI
Classifier: Development Status :: 3 - Alpha
Classifier: Intended Audience :: Developers
Classifier: Programming Language :: Python :: 3
Classifier: Operating System :: OS Independent
Classifier: Topic :: Software Development :: Libraries :: Python Modules
Classifier: Topic :: Scientific/Engineering :: Artificial Intelligence
Requires-Python: >=3.6
License-File: LICENSE
Dynamic: author
Dynamic: author-email
Dynamic: classifier
Dynamic: description
Dynamic: description-content-type
Dynamic: home-page
Dynamic: keywords
Dynamic: license
Dynamic: license-file
Dynamic: requires-python
Dynamic: summary
